courier_python/__init__.py
courier_python/cli.py
courier_python/courier_python.py
courier_python-0.1.0.dist-info/LICENSE
courier_python-0.1.0.dist-info/METADATA
courier_python-0.1.0.dist-info/WHEEL
courier_python-0.1.0.dist-info/entry_points.txt
courier_python-0.1.0.dist-info/top_level.txt
courier_python-0.1.0.dist-info/RECORD
